edw.logger-1.15-py2.7-nspkg.pth
edw/logger/__init__.py
edw/logger/config.py
edw/logger/configure.zcml
edw/logger/decorators.py
edw/logger/util.py
edw/logger/catalog/__init__.py
edw/logger/events/__init__.py
edw/logger/events/base.py
edw/logger/events/configure.zcml
edw/logger/events/content.py
edw/logger/events/db_commit.py
edw/logger/events/interfaces.py
edw/logger/patches/__init__.py
edw/logger/patches/error.py
edw/logger/patches/publisher.py
edw.logger-1.15.dist-info/DESCRIPTION.rst
edw.logger-1.15.dist-info/METADATA
edw.logger-1.15.dist-info/RECORD
edw.logger-1.15.dist-info/WHEEL
edw.logger-1.15.dist-info/entry_points.txt
edw.logger-1.15.dist-info/metadata.json
edw.logger-1.15.dist-info/namespace_packages.txt
edw.logger-1.15.dist-info/top_level.txt
