Metadata-Version: 2.0
Name: edw.logger
Version: 1.15
Summary: Zope logging package.
Home-page: https://github.com/eaudeweb/edw.logger
Author: David Batranu
Author-email: david.batranu@eaudeweb.ro
License: GPL
Keywords: edw logging package
Platform: UNKNOWN
Classifier: Programming Language :: Python
Classifier: Framework :: Zope2
Requires-Dist: setuptools
